graylog/__init__.py
graylog/handlers.py
graylog/http.py
graylog/tcp.py
graylog/tls.py
graylog/udp.py
tests/__init__.py
tests/test_main.py
python_graylog-0.3.0.dist-info/LICENSE
python_graylog-0.3.0.dist-info/METADATA
python_graylog-0.3.0.dist-info/WHEEL
python_graylog-0.3.0.dist-info/top_level.txt
python_graylog-0.3.0.dist-info/RECORD
